graph_id_cpp.cpython-312-x86_64-linux-gnu.so
graph_id_core-0.1.17.dist-info/WHEEL
graph_id_core-0.1.17.dist-info/METADATA
graph_id_core-0.1.17.dist-info/RECORD
graph_id/__init__.py
graph_id/commands/gid.py
graph_id/app/maker.py
graph_id/core/graph_id.py
graph_id/core/distance_clustering_graph_id.py
graph_id/core/__init__.py
graph_id/analysis/local_env.py
graph_id/analysis/compositional_sequence.py
graph_id/analysis/__init__.py
graph_id/analysis/graphs.py
