Metadata-Version: 2.4
Name: graph-id-core
Version: 0.1.17
Summary: 
Author: Koki Muraoka
Author-email: muraok_k@chemsys.t.u-tokyo.ac.jp
Requires-Python: >=3.10,<3.14
Classifier: Programming Language :: Python :: 3
Classifier: Programming Language :: Python :: 3.10
Classifier: Programming Language :: Python :: 3.11
Classifier: Programming Language :: Python :: 3.12
Classifier: Programming Language :: Python :: 3.13
Requires-Dist: pybind11 (==2.11.1)
Requires-Dist: pymatgen (>=2025.10.7,<2026.0.0)
Requires-Dist: scikit-learn (>=0.24.1)
